mmsplice/__init__.py
mmsplice/exon_dataloader.py
mmsplice/junction_dataloader.py
mmsplice/layers.py
mmsplice/main.py
mmsplice/mmsplice.py
mmsplice/mtsplice.py
mmsplice/utils.py
mmsplice/vcf_dataloader.py
mmsplice/models/Acceptor.h5
mmsplice/models/Donor.h5
mmsplice/models/Exon.h5
mmsplice/models/Exon_prime3.h5
mmsplice/models/Intron3.h5
mmsplice/models/Intron5.h5
mmsplice/models/Pathogenicity.pkl
mmsplice/models/grch37_exons.csv.gz
mmsplice/models/grch38_exons.csv.gz
mmsplice/models/gtex_psi_map37_ranges.csv.gz
mmsplice/models/gtex_psi_map_ranges.csv.gz
mmsplice/models/linear_model.pkl
mmsplice/models/mtsplice0.h5
mmsplice/models/mtsplice1.h5
mmsplice/models/mtsplice2.h5
mmsplice/models/mtsplice3.h5
mmsplice/models/mtsplice4.h5
mmsplice/models/mtsplice5.h5
mmsplice/models/mtsplice6.h5
mmsplice/models/mtsplice7.h5
mmsplice/models/mtsplice_deep0.h5
mmsplice/models/mtsplice_deep1.h5
mmsplice/models/mtsplice_deep2.h5
mmsplice/models/mtsplice_deep3.h5
mmsplice/models/splicing_efficiency.pkl
mmsplice-2.4.0.dist-info/AUTHORS.rst
mmsplice-2.4.0.dist-info/LICENSE
mmsplice-2.4.0.dist-info/METADATA
mmsplice-2.4.0.dist-info/WHEEL
mmsplice-2.4.0.dist-info/entry_points.txt
mmsplice-2.4.0.dist-info/top_level.txt
mmsplice-2.4.0.dist-info/RECORD
