Metadata-Version: 2.1
Name: mmsplice
Version: 2.4.0
Summary: Predict splicing variant effect from VCF
Home-page: https://github.com/gagneurlab/mmsplice
Author: Jun Cheng, Muhammed Hasan Çelik
Author-email: chengju@in.tum.de, muhammedhasancelik@gmail.com
License: MIT license
Keywords: mmsplice
Platform: UNKNOWN
Classifier: Development Status :: 2 - Pre-Alpha
Classifier: Intended Audience :: Developers
Classifier: License :: OSI Approved :: MIT License
Classifier: Natural Language :: English
Classifier: Programming Language :: Python :: 3.4
Classifier: Programming Language :: Python :: 3.5
Classifier: Programming Language :: Python :: 3.6
License-File: LICENSE
License-File: AUTHORS.rst
Requires-Dist: setuptools
Requires-Dist: kipoiseq
Requires-Dist: cyvcf2
Requires-Dist: tensorflow
Requires-Dist: scipy
Requires-Dist: pandas
Requires-Dist: pyfaidx
Requires-Dist: tqdm
Requires-Dist: click
Requires-Dist: cyvcf2 (<=0.30.15)
Requires-Dist: pyranges (<0.0.126,>=0.0.71)
